polestar/__init__.py
polestar/commandmanager.py
polestar/os/__init__.py
polestar/project/__init__.py
polestar/project/projectmanager.py
polestar/project/data/__init__.py
polestar/project/data/configurationdata.py
polestar/project/data/packagedata.py
polestar/project/data/projectdata.py
polestar-0.0.5.dist-info/LICENSE
polestar-0.0.5.dist-info/METADATA
polestar-0.0.5.dist-info/WHEEL
polestar-0.0.5.dist-info/entry_points.txt
polestar-0.0.5.dist-info/top_level.txt
polestar-0.0.5.dist-info/RECORD
