Metadata-Version: 2.1
Name: polestar
Version: 0.0.5
Summary: Python Project Management
Home-page: https://sidoware.com
Author: sidoware
Author-email: developer@sidoware.com
Classifier: Programming Language :: Python :: 3
Classifier: License :: OSI Approved :: MIT License
Classifier: Operating System :: OS Independent
Requires-Python: >=3.7
License-File: LICENSE
Requires-Dist: spxl
